[
  { "id": "69b8d36d96c738f378addd02", "names": ["Rory Weston"] },
  { "id": "6432528758a77fa2d4bec2b1", "names": ["*** Shivam ***"] },
  { "id": "69816c67e2b021313f732d53", "names": ["Aashay Shah"] },
  { "id": "5f4df1e6c1f38700041d7217", "names": ["Arun Nair"] },
  { "id": "65a9971d376334e34dea979b", "names": ["Merenna Amarasinghe"] },
  { "id": "5efae3add94cf4000415c266", "names": ["Jibin Jose"] },
  { "id": "69ebbe9166081590d807a9bf", "names": ["Ray Lugsanay"] },
  { "id": "67e245d31d8f35f307768195", "names": ["Abhishek Nambiar"] },
  { "id": "5ef1b55319a24f000420d6a5", "names": ["Martin Hedlund"] },
  { "id": "6236cd7fbee2780331789a76", "names": ["Han Lin"] },
  { "id": "5f08ce4b861be40004154e67", "names": ["Carter Wu"] },
  { "id": "661e1f2ee3c6e87ef09cfada", "names": ["Aby George"] },
  { "id": "5d25228ab8ffde00045808a4", "names": ["Trevor Hollings"] },
  { "id": "5cf83f5627b7240004667ef2", "names": ["Shane Ringrose"] },
  { "id": "64ead50c9d7436959a1a61cb", "names": ["Tristan Fewtrell"] },
  { "id": "5f08cdaf861be40004154def", "names": ["Jackie Wu"] },
  { "id": "66c12375cc45f0a8975ca68f", "names": ["Kenzie Peachey"] },
  { "id": "67beaa56e0a13d35966773d8", "names": ["Shashank Pai"] },
  { "id": "64af69c003d034903e348434", "names": ["Vilius Vaivada"] },
  { "id": "68931784a8e82bd15e841ca2", "names": ["Dee Phetsomphou"] },
  { "id": "63479c8621b12b08f1608e2b", "names": ["Roland Fewtrell"] },
  { "id": "5e5880cfe3aa150004957aee", "names": ["Karsten Thomsen"] },
  { "id": "673c12e93b687435b1675567", "names": ["Jeremy Thomassen"] },
  { "id": "69eb187faf102100b654336b", "names": ["Noushad Kasim"] },
  { "id": "6875fa4ce49fa050390a89cd", "names": ["Barry Clarke"] },
  { "id": "68ad77e7f6937e65fc03eabe", "names": ["Eric Hehne"] },
  { "id": "66a8913809387a4ca1d010c6", "names": ["Chia BingHon"] },
  { "id": "64f50246b1b24deb499e7a32", "names": ["Aiko Gumban"] },
  { "id": "65cd7c01028e6e3f5d88871f", "names": ["Nathaiel Enguerra"] },
  { "id": "5e5880cfe3aa150004957b07", "names": ["Nick Andrews??"] },
  { "id": "5e5880cfe3aa150004957aeb", "names": ["Kareen Hansard"] },
  { "id": "61091f879f07c100040660b9", "names": ["Mani Sidhu"] },
  { "id": "68fea9147eb4a3f1fb9af45b", "names": ["Manulal Sankaran"] },
  { "id": "66f2654d0c8a5fe442254c47", "names": ["Karlos Hanna"] },
  { "id": "64b63af179af7e37f419e49e", "names": ["Jobin Jose"] },
  { "id": "6285e55c6c92f321638df878", "names": ["Jiljo George"] },
  { "id": "5efd6766eb081600040d7bde", "names": ["Isaac Hong"] },
  { "id": "667bec26d20c50f548c6b1c1", "names": ["Tricia Liew"] },
  { "id": "663f198cbbb1ad36893fc714", "names": ["Dominc Tapalla"] },
  { "id": "67f4e8f2d3357abc54936bcb", "names": ["Marie Hemingway"] },
  { "id": "5f32403119d3d50004dfcb76", "names": ["Shyju John"] },
  { "id": "62ec95a996bd3466064eaa7b", "names": ["Nelson Hall"] },
  { "id": "5e83c754b9061300044ded80", "names": ["Anna Shrubshall"] },
  { "id": "650920f869394e991e953fe4", "names": ["Isaac Xie"] },
  { "id": "636ec90f1e6d385edf3837b8", "names": ["Emil John"] },
  { "id": "6253b695e673883b067743d5", "names": ["Albyjo Jose"] },
  { "id": "6549ad9dd684c2753199bdc4", "names": ["Simon Xie"] },
  { "id": "67d3480e98528923f54c17b2", "names": ["Jeet Arora"] },
  { "id": "5e5880cfe3aa150004957ab8", "names": ["Dave Jackson"] },
  { "id": "65d41be7e46c8a731dd4da78", "names": ["Joshua Jijo"] },
  { "id": "6508148183259bd88c966244", "names": ["Joanne Small"] },
  { "id": "68e33a710b0ba03a771659f2", "names": ["Kayil Ward-Ruddell"] },
  { "id": "6577e9cf74c5f6049966356a", "names": ["Anuj Sharma"] },
  { "id": "60125eca38bc530004792624", "names": ["Jency Jacob"] },
  { "id": "637ad4971676eeca4e2f1b17", "names": ["Muska Lee"] },
  { "id": "5f321f0219d3d50004de411a", "names": ["Jenelyn Frane"] },
  { "id": "6006715abd0a9f0004a40012", "names": ["Jerin Jose"] },
  { "id": "5fa255f9df99c40004464671", "names": ["Lachlan Smith"] },
  { "id": "66fb8fefacd6463e56f8256f", "names": ["Dre King"] },
  { "id": "631ff0abaef970a71cbbc0af", "names": ["Emil Zaharison"] },
  { "id": "6180ae04d5de722b4d96c8d3", "names": ["Alex Liu"] },
  { "id": "5fa23d28df99c40004452555", "names": ["Toby Ringrose"] },
  { "id": "65a36b986a51dc28d0ae39d1", "names": ["Sean Kam"] },
  { "id": "69ebf623c9364fcca1195bf4", "names": ["Brent Javier"] },
  { "id": "6142ca2526bc1d0004e0df54", "names": ["Taanvi Maharaj"] },
  { "id": "68db0792bd6c4b519d0582a4", "names": ["Pawan Goundar"] },
  { "id": "6821a4026912e303dde3ae00", "names": ["Winston Lee"] },
  { "id": "650ab4224f45b45802a37d99", "names": ["James Wu"] },
  { "id": "66b1cbdfefa8a244bfbf9135", "names": ["Neil Ganatra"] },
  { "id": "5e5880cfe3aa150004957b1e", "names": ["Jen Brown"] },
  { "id": "66b1cc68400652d8a1c9a3da", "names": ["Naduli Goonatillake"] },
  { "id": "6821793c86c616fb70afdd0a", "names": ["Amanda Lee"] },
  { "id": "64746180b76e591453f3e7bf", "names": ["Binu Thankachan"] },
  { "id": "65d6bdd391a563427578b1d6", "names": ["Brenda Smith"] },
  { "id": "64c8c5650496f58c2fcd8412", "names": ["Emily Ha"] },
  { "id": "640949e0131e8f5e9f361923", "names": ["Seong Kim"] },
  { "id": "5e5880cfe3aa150004957af4", "names": ["Lance Newby"] },
  { "id": "67ca389785d6e3b661e21f6b", "names": ["Tura Rata"] },
  { "id": "659e02176822fe7d9cd56c19", "names": ["Alan Xie"] },
  { "id": "68e33a710b0ba03a77165a05", "names": ["Stephen Pashley"] },
  { "id": "67b420aadd33f754334d1b76", "names": ["Stephaine Wei"] },
  { "id": "5f3241c019d3d50004dfd7a1", "names": ["John Cheah"] },
  { "id": "683eba494a2557d646ebbf2f", "names": ["Ray Petrie"] },
  { "id": "6142ca2526bc1d0004e0df56", "names": ["Shruti Maharaj"] },
  { "id": "6491683da2aa29f1782336dd", "names": ["Lusia Ioane"] },
  { "id": "6887da9ed163e9a3ab16be18", "names": ["Kodyn Brown"] },
  { "id": "5fb34ab7b11ae100045e242a", "names": ["Priyal Sharma"] },
  { "id": "620b27f4f4098886140a1395", "names": ["Jamie Cramer"] },
  { "id": "635b492e750bfd21fb89dc54", "names": ["Sunil KK"] },
  { "id": "60c2e3166ee2c4000430b585", "names": ["Cameron Scott"] },
  { "id": "5f321d2119d3d50004de2309", "names": ["David Ma"] },
  { "id": "64f56873969a9bc5c8612703", "names": ["Darrell Martin"] },
  { "id": "68f71f1ead578bd86853f5a8", "names": ["Midhun Thomas"] },
  { "id": "5edf16ffabceb10004007187", "names": ["Grace Silatolu"] },
  { "id": "68231b4ce4e57aa739b55e03", "names": ["Aaron Yan"] },
  { "id": "5f321f7b19d3d50004de439f", "names": ["Wageesha Kuruppu"] },
  { "id": "65cae76f9f580b2cea5d7a8c", "names": ["Atashia Gozun"] },
  { "id": "5e5880cfe3aa150004957abe", "names": ["Deidre Sterling"] },
  { "id": "5f32200119d3d50004de48a0", "names": ["Amia Ringrose"] },
  { "id": "682fda9a4a74c31a70a04452", "names": ["Sai Veikoso"] },
  { "id": "66b1d18d7d5450606468f1b1", "names": ["David Moratti"] },
  { "id": "661d98cedcc66a68fed2c470", "names": ["Catherine Mitchell"] },
  { "id": "6180ae68d5de722b4d96d098", "names": ["Fraser Pugh"] },
  { "id": "645b38762fc455bfc4888a14", "names": ["Noah Hong"] },
  { "id": "68198bfd7582429935194ff7", "names": ["Jan Loganimoce"] },
  { "id": "654462893fb68b6d0ba57ba8", "names": ["Francisco Junior"] },
  { "id": "61ad8f29f47723405509dffb", "names": ["Christopher Kim"] },
  { "id": "601cece5d89beb0004e778d4", "names": ["Taylor Warren"] },
  { "id": "66361a6e35baf38c70c10a38", "names": ["Swetlana Pious"] },
  { "id": "661ac7fe3999d97987e49f76", "names": ["Koro Heremia"] },
  { "id": "672055417b0d009362e58d0f", "names": ["Zac Watson"] },
  { "id": "67bd4e5fc5a7a0a9abf3c2a3", "names": ["Annie Tay"] },
  { "id": "601cece5d89beb0004e778d0", "names": ["Jacob Warren"] },
  { "id": "601cece5d89beb0004e778ce", "names": ["Jannelle Rodgers"] },
  { "id": "6812160d92358ee5a00f8984", "names": ["Karizza Lyn Arzadon"] },
  { "id": "6847f4bab9377b9ea97f6812", "names": ["Priya O'Neill"] },
  { "id": "6a30f467eefd3d9d17c09583", "names": ["*** Joshin Jacob Johnson ***"] },
  { "id": "66dfc563d137dca063e1113b", "names": ["*** Lennon Lee ***"] },
  { "id": "63f6db356d5f1d8cdb1a4782", "names": ["Amber Lorigan"] },
  { "id": "621d8f80870b8a10a08a1596", "names": ["*** Remus ***"] },
  { "id": "6983af92407b5ff64a3c906d", "names": ["Lexi Laybourn"] },
  { "id": "5e5880cfe3aa150004957afb", "names": ["Mark Duffield"] },
  { "id": "69f995fa29205bc277ff4562", "names": ["Madhav Kapoor"] },
  { "id": "6539ecaa9349d1ca09a38f58", "names": ["Jackson Finlayson"] }
]
